commpy/__init__.py
commpy/channels.py
commpy/filters.py
commpy/impairments.py
commpy/links.py
commpy/modulation.py
commpy/sequences.py
commpy/utilities.py
commpy/wifi80211.py
commpy/channelcoding/__init__.py
commpy/channelcoding/algcode.py
commpy/channelcoding/convcode.py
commpy/channelcoding/gfields.py
commpy/channelcoding/interleavers.py
commpy/channelcoding/ldpc.py
commpy/channelcoding/turbo.py
commpy/channelcoding/tests/__init__.py
commpy/channelcoding/tests/test_algcode.py
commpy/channelcoding/tests/test_convcode.py
commpy/channelcoding/tests/test_gfields.py
commpy/channelcoding/tests/test_ldpc.py
commpy/tests/__init__.py
commpy/tests/test_channels.py
commpy/tests/test_links.py
commpy/tests/test_modulation.py
commpy/tests/test_sequences.py
commpy/tests/test_utilities.py
commpy/tests/test_wifi80211.py
scikit_commpy-0.6.0.data/scripts/runner
scikit_commpy-0.6.0.dist-info/LICENSE.txt
scikit_commpy-0.6.0.dist-info/METADATA
scikit_commpy-0.6.0.dist-info/WHEEL
scikit_commpy-0.6.0.dist-info/top_level.txt
scikit_commpy-0.6.0.dist-info/RECORD
