Metadata-Version: 2.1
Name: scikit-commpy
Version: 0.6.0
Summary: Digital Communication Algorithms with Python
Home-page: http://veeresht.github.com/CommPy
Maintainer: Veeresh Taranalli & Bastien Trotobas
Maintainer-email: veeresht@gmail.com
License: BSD 3-Clause
Platform: UNKNOWN
Classifier: Development Status :: 4 - Beta
Classifier: Intended Audience :: Science/Research
Classifier: Intended Audience :: Telecommunications Industry
Classifier: Operating System :: Unix
Classifier: Programming Language :: Python
Classifier: Topic :: Scientific/Engineering
Classifier: Topic :: Software Development
Requires-Python: >=3.2
Requires-Dist: numpy
Requires-Dist: scipy
Requires-Dist: matplotlib
